README.md
setup.py
lw_spapi.egg-info/PKG-INFO
lw_spapi.egg-info/SOURCES.txt
lw_spapi.egg-info/dependency_links.txt
lw_spapi.egg-info/requires.txt
lw_spapi.egg-info/top_level.txt
spapi/__init__.py
spapi/aws_sig_v4.py
spapi/cache.py
spapi/client.py
spapi/credential_provider.py
spapi/exceptions.py
spapi/lock.py
spapi/marketplaces.py