Metadata-Version: 2.1
Name: lw-spapi
Version: 1.0.7
Summary: A wrapper to access Amazon Selling Partner API with an easy-to-use SDK.
Home-page: https://www.lifewit.cn
Author: liftwit
Author-email: jiangzuojia@lifewit.com
License: UNKNOWN
Platform: UNKNOWN
